clickpy/__init__.py
clickpy/__main__.py
clickpy/exception.py
clickpy/strategy/__init__.py
clickpy/strategy/_strategy.py
clickpy-0.12.dist-info/licenses/LICENSE
clickpy-0.12.dist-info/METADATA
clickpy-0.12.dist-info/WHEEL
clickpy-0.12.dist-info/top_level.txt
clickpy-0.12.dist-info/RECORD
