Metadata-Version: 2.4
Name: clickpy
Version: 0.12
Summary: Add your description here
Requires-Python: >=3.13
License-File: LICENSE
Requires-Dist: pyautogui>=0.9.54
Requires-Dist: typer>=0.16.1
Dynamic: license-file
